rustbpe-0.1.0.dist-info/METADATA
rustbpe-0.1.0.dist-info/WHEEL
rustbpe-0.1.0.dist-info/licenses/LICENSE
rustbpe/__init__.py
rustbpe/rustbpe.cpython-311-darwin.so
rustbpe-0.1.0.dist-info/RECORD
