Metadata-Version: 2.4
Name: rustbpe
Version: 0.1.0
Classifier: Programming Language :: Rust
Classifier: Programming Language :: Python :: Implementation :: CPython
Classifier: Programming Language :: Python :: 3
Classifier: Programming Language :: Python :: 3.9
Classifier: Programming Language :: Python :: 3.10
Classifier: Programming Language :: Python :: 3.11
Classifier: Programming Language :: Python :: 3.12
Classifier: Programming Language :: Python :: 3.13
Requires-Dist: pytest>=8.0 ; extra == 'dev'
Requires-Dist: pytest-cov>=4.0 ; extra == 'dev'
Provides-Extra: dev
License-File: LICENSE
Summary: A BPE (Byte Pair Encoding) tokenizer written in Rust with Python bindings
License: MIT
Requires-Python: >=3.9
